pianno/__init__.py
pianno/_annotation_improvement.py
pianno/_auto_pattern_recognition.py
pianno/_calculate_energy.py
pianno/_create_mask_image.py
pianno/_create_pianno_object.py
pianno/_label_renew.py
pianno/_posteriori_inference.py
pianno/_priori_initialization.py
pianno/_saver.py
pianno/_search_best_params.py
pianno/_spatial_pattern_recognition.py
pianno/_tuner.py
pianno/model.py
pianno-1.0.5.dist-info/METADATA
pianno-1.0.5.dist-info/WHEEL
pianno-1.0.5.dist-info/top_level.txt
pianno-1.0.5.dist-info/RECORD
